MANIFEST.in
README.md
meta.json
setup.cfg
setup.py
en_neuralcoref/__init__.py
en_neuralcoref/meta.json
en_neuralcoref.egg-info/PKG-INFO
en_neuralcoref.egg-info/SOURCES.txt
en_neuralcoref.egg-info/dependency_links.txt
en_neuralcoref.egg-info/not-zip-safe
en_neuralcoref.egg-info/requires.txt
en_neuralcoref.egg-info/top_level.txt
en_neuralcoref/en_neuralcoref-2.1.0/meta.json
en_neuralcoref/en_neuralcoref-2.1.0/sentencizer.json
en_neuralcoref/en_neuralcoref-2.1.0/tokenizer
en_neuralcoref/en_neuralcoref-2.1.0/ner/cfg
en_neuralcoref/en_neuralcoref-2.1.0/ner/model
en_neuralcoref/en_neuralcoref-2.1.0/ner/moves
en_neuralcoref/en_neuralcoref-2.1.0/neuralcoref/cfg
en_neuralcoref/en_neuralcoref-2.1.0/neuralcoref/pairs_model
en_neuralcoref/en_neuralcoref-2.1.0/neuralcoref/single_model
en_neuralcoref/en_neuralcoref-2.1.0/neuralcoref/static_vectors/key2row
en_neuralcoref/en_neuralcoref-2.1.0/neuralcoref/static_vectors/vectors
en_neuralcoref/en_neuralcoref-2.1.0/neuralcoref/tuned_vectors/key2row
en_neuralcoref/en_neuralcoref-2.1.0/neuralcoref/tuned_vectors/vectors
en_neuralcoref/en_neuralcoref-2.1.0/parser/cfg
en_neuralcoref/en_neuralcoref-2.1.0/parser/model
en_neuralcoref/en_neuralcoref-2.1.0/parser/moves
en_neuralcoref/en_neuralcoref-2.1.0/tagger/cfg
en_neuralcoref/en_neuralcoref-2.1.0/tagger/model
en_neuralcoref/en_neuralcoref-2.1.0/tagger/tag_map
en_neuralcoref/en_neuralcoref-2.1.0/vocab/key2row
en_neuralcoref/en_neuralcoref-2.1.0/vocab/lexemes.bin
en_neuralcoref/en_neuralcoref-2.1.0/vocab/strings.json
en_neuralcoref/en_neuralcoref-2.1.0/vocab/vectors