Metadata-Version: 2.1
Name: en-neuralcoref
Version: 2.1.1
Summary: Pipeline extension for spaCy which annotates and resolves coreference clusters using a neural network.
Home-page: https://robo-ai.com/
Author: Robo.AI
Author-email: info@robo-ai.com
License: MIT
Platform: UNKNOWN
